LICENSE
utilityai/__init__.py
utilityai/chat.py
utilityai/code.py
utilityai/core.py
utilityai/model.py
utilityai-1.0.1.dist-info/LICENSE
utilityai-1.0.1.dist-info/METADATA
utilityai-1.0.1.dist-info/WHEEL
utilityai-1.0.1.dist-info/RECORD
