Metadata-Version: 2.1
Name: utilityai
Version: 1.0.1
Summary: This package brings language model capabilities into the coding environment, providing a variety of functionalities.
Home-page: https://github.com/navid-matinmo/utilityai
License: MIT
Keywords: LLM,AI
Author: Navid Matin Moghaddam
Author-email: navid.matinmo@gmail.com
Requires-Python: >=3.0
Classifier: License :: OSI Approved :: MIT License
Classifier: Operating System :: OS Independent
Classifier: Programming Language :: Python :: 3
Classifier: Programming Language :: Python :: 3.4
Classifier: Programming Language :: Python :: 3.5
Classifier: Programming Language :: Python :: 3.6
Classifier: Programming Language :: Python :: 3.7
Classifier: Programming Language :: Python :: 3.8
Classifier: Programming Language :: Python :: 3.9
Classifier: Programming Language :: Python :: 3.10
Classifier: Programming Language :: Python :: 3.11
Classifier: Programming Language :: Python :: 3.12
Requires-Dist: huggingface_hub (>=0.13.0)
Requires-Dist: numpy (>=1.21.2)
Requires-Dist: onnxruntime-genai (>=0.2.0) ; sys_platform == "linux"
Requires-Dist: onnxruntime-genai (>=0.2.0) ; sys_platform == "win32"
Requires-Dist: onnxruntime-genai (>=0.3.0rc1) ; sys_platform != "win32" and sys_platform != "linux"
Project-URL: Documentation, https://github.com/navid-matinmo/utilityai
Project-URL: Repository, https://github.com/navid-matinmo/utilityai
Project-URL: issues, https://github.com/navid-matinmo/utilityai/issues
